ezconfiguration/__init__.py
ezconfiguration/config_manager.py
ezconfiguration-0.0.2.dist-info/LICENSE
ezconfiguration-0.0.2.dist-info/METADATA
ezconfiguration-0.0.2.dist-info/WHEEL
ezconfiguration-0.0.2.dist-info/top_level.txt
ezconfiguration-0.0.2.dist-info/RECORD
