Metadata-Version: 2.1
Name: ezconfiguration
Version: 0.0.2
Summary: This is an easy way to a configuration file in json format.
Home-page: https://github.com/datanooblol/ezconfiguration
Author: datanooblol
Author-email: data.noob.lol@gmail.com
License: MIT
Keywords: ['python3','ez','config']
Classifier: Programming Language :: Python :: 3
Classifier: License :: OSI Approved :: MIT License
Classifier: Operating System :: OS Independent
Requires-Python: >=3.0
License-File: LICENSE
